[
	{ "s": "PADRE", "p": [13] },
	{ "s": "PARA", "p": [2, 6, 13, 14, 5] },
	{ "s": "PARED", "p": [14] },
	{ "s": "PASADO", "p": [13] },
	{ "s": "PATRONES", "p": [5] },
	{ "s": "PEQUEÑA", "p": [6] },
	{ "s": "PERDIÓ", "p": [5] },
	{ "s": "PERMANENTEMENTE", "p": [2] },
	{ "s": "PERO", "p": [6, 5] },
	{ "s": "PERSONAJES", "p": [13] },
	{ "s": "PETICIONES", "p": [13] },
	{ "s": "PODER", "p": [2] },
	{ "s": "PODRÍA", "p": [2] },
	{ "s": "POR", "p": [14, 13, 5, 6, 2] },
	{ "s": "POSEIDON", "p": [14] },
	{ "s": "POSIBILIDAD", "p": [14] },
	{ "s": "PREDECIR", "p": [5] },
	{ "s": "PREOCUPA", "p": [13] },
	{ "s": "PRESENTAN", "p": [13] },
	{ "s": "PRESIONA", "p": [6] },
	{ "s": "PRESIONADO", "p": [6] },
	{ "s": "PRIMER", "p": [14] },
	{ "s": "PRIMERAS", "p": [5] },
	{ "s": "PRIMERO", "p": [5] },
	{ "s": "PRINCIPAL", "p": [6, 1] },
	{ "s": "PRINCIPALES", "p": [13] },
	{ "s": "PRINCIPE", "p": [13] },
	{ "s": "PROBABILIDADES", "p": [14] },
	{ "s": "PROBADO", "p": [13] },
	{ "s": "PROFUNDAMENTE", "p": [13] },
	{ "s": "PROFUNDIDADES", "p": [5] },
	{ "s": "PROPIO", "p": [13] },
	{ "s": "PROTAGONISTA", "p": [13] },
	{ "s": "PROVOCA", "p": [14] },
	{ "s": "PROYECTILES", "p": [14] },
	{ "s": "PRÓXIMOS", "p": [5] },
	{ "s": "PUEDAN", "p": [14] },
	{ "s": "PUEDE", "p": [5, 13, 6, 2] },
	{ "s": "PUEDEN", "p": [5, 6] },
	{ "s": "PUEDES", "p": [5, 14] },
	{ "s": "PUERTA", "p": [5, 2] },
	{ "s": "PUÑOS", "p": [11, 6] },
	{ "s": "PÁGINA", "p": [1] }
]